bip32keys/__init__.py
bip32keys/bip32NetworkKeys.py
bip32keys/bip32addresses.py
bip32keys/bip32keys.py
bip32keys/r8_ethereum/__init__.py
bip32keys/r8_ethereum/r8_eth.py
pywallet/__init__.py
pywallet/_version.py
pywallet/network.py
pywallet/wallet.py
pywallet/utils/__init__.py
pywallet/utils/bip32.py
pywallet/utils/ethereum.py
pywallet/utils/keys.py
pywallet/utils/utils.py
qtum_utils/__init__.py
qtum_utils/qtum.py
qtum_utils/qtum_tests.py
tornado_components/__init__.py
tornado_components/decorators.py
tornado_components/keys.py
tornado_components/mongo.py
tornado_components/timestamp.py
tornado_components/web.py
tornado_components/auth/__init__.py
tornado_components/auth/handler.py
tornado_components/auth/utils.py
robin8_utils-0.4.26.dist-info/LICENSE
robin8_utils-0.4.26.dist-info/METADATA
robin8_utils-0.4.26.dist-info/WHEEL
robin8_utils-0.4.26.dist-info/top_level.txt
robin8_utils-0.4.26.dist-info/RECORD
