Metadata-Version: 2.1
Name: robin8-utils
Version: 0.4.26
Summary: Utils used in Robin8 projects
Home-page: https://github.com/Robin8Put/pmes/tree/master/utils
Author: Robin8
Author-email: vvasyuk@robin8.com
License: UNKNOWN
Platform: UNKNOWN
Classifier: Programming Language :: Python :: 3
Classifier: License :: OSI Approved :: Apache Software License
Classifier: Operating System :: OS Independent
Requires-Dist: apply-defaults
Requires-Dist: attrdict
Requires-Dist: base58check
Requires-Dist: bip32utils
Requires-Dist: certifi
Requires-Dist: chardet
Requires-Dist: cytoolz
Requires-Dist: ecdsa
Requires-Dist: eth-abi
Requires-Dist: eth-account
Requires-Dist: eth-hash
Requires-Dist: eth-keyfile
Requires-Dist: eth-keys
Requires-Dist: eth-rlp
Requires-Dist: eth-typing
Requires-Dist: eth-utils
Requires-Dist: fastecdsa
Requires-Dist: funcsigs
Requires-Dist: hexbytes
Requires-Dist: idna
Requires-Dist: jsonrpcclient (<=2.6.0)
Requires-Dist: jsonrpcserver
Requires-Dist: jsonschema
Requires-Dist: lru-dict
Requires-Dist: motor
Requires-Dist: parsimonious
Requires-Dist: pycryptodome
Requires-Dist: pymongo
Requires-Dist: requests
Requires-Dist: rlp
Requires-Dist: pysha3
Requires-Dist: six
Requires-Dist: toolz
Requires-Dist: tornado
Requires-Dist: urllib3
Requires-Dist: web3
